sca_test/__init__.py
sca_test/core.py
sca_test/dataloader.py
sca_test/objective.py
sca_test-0.1.0.dist-info/licenses/LICENSE.txt
sca_test-0.1.0.dist-info/METADATA
sca_test-0.1.0.dist-info/WHEEL
sca_test-0.1.0.dist-info/top_level.txt
sca_test-0.1.0.dist-info/RECORD
