Metadata-Version: 2.4
Name: sca_test
Version: 0.1.0
Summary: Automatic augmentation
Author: Anna Kolesnikova
Author-email: Kolesnikova Anna <anny_ko66@mail.ru>
License: MIT
Project-URL: Homepage, https://github.com/KolesnikovaAnna/sca_test
Classifier: Programming Language :: Python :: 3
Classifier: License :: OSI Approved :: MIT License
Classifier: Operating System :: OS Independent
Requires-Python: >=3.7
License-File: LICENSE.txt
Requires-Dist: numpy>=1.21
Dynamic: author
Dynamic: license-file
Dynamic: requires-python
